woe_scoring/__init__.py
woe_scoring/core/__init__.py
woe_scoring/core/binning/__init__.py
woe_scoring/core/binning/functions.py
woe_scoring/core/main.py
woe_scoring/core/model/__init__.py
woe_scoring/core/model/functions.py
woe_scoring/core/model/model.py
woe_scoring/core/model/selector.py
woe_scoring-2.0.0.dist-info/LICENSE
woe_scoring-2.0.0.dist-info/METADATA
woe_scoring-2.0.0.dist-info/WHEEL
woe_scoring-2.0.0.dist-info/RECORD
