Metadata-Version: 2.1
Name: woe_scoring
Version: 2.0.0
Summary: Weight Of Evidence Transformer and LogisticRegression model with scikit-learn API
License: MIT
Author: Stroganov Kirill
Author-email: kiraplenkin@gmail.com
Requires-Python: >=3.9,<4.0
Classifier: License :: OSI Approved :: MIT License
Classifier: Programming Language :: Python :: 3
Classifier: Programming Language :: Python :: 3.9
Classifier: Programming Language :: Python :: 3.10
Classifier: Programming Language :: Python :: 3.11
Classifier: Programming Language :: Python :: 3.12
Classifier: Programming Language :: Python :: 3.13
Requires-Dist: joblib (>=1.1.0)
Requires-Dist: lxml (>=4.8.0)
Requires-Dist: numpy (>=1.19.5)
Requires-Dist: pandas (>=1.2.2)
Requires-Dist: scikit-learn (>=0.24.1)
Requires-Dist: scipy (>=1.6.1)
Requires-Dist: statsmodels (>=0.12.2)
Requires-Dist: xlsxwriter (>=3.0.0)
